Metadata-Version: 2.1
Name: fundamentos
Version: 1.5
Summary: Download Bovespa Stock Market fundamentals with Python.
Home-page: https://github.com/NathanMoura/fundamentos
Author: Nathan de Moura Vieira
Author-email: nathanmoura194@gmail.com
License: MIT
Download-URL: https://github.com/NathanMoura/fundamentos/archive/v1.5.tar.gz
Keywords: pandas,finance,fundamentals,bovespa
Platform: UNKNOWN
Classifier: Development Status :: 5 - Production/Stable
Classifier: Operating System :: OS Independent
Classifier: Intended Audience :: Developers
Classifier: Topic :: Office/Business :: Financial
Classifier: Topic :: Office/Business :: Financial :: Investment
Classifier: Topic :: Software Development :: Libraries
Classifier: Topic :: Software Development :: Libraries :: Python Modules
Classifier: Topic :: Software Development :: Build Tools
Classifier: License :: OSI Approved :: MIT License
Classifier: Programming Language :: Python :: 3.6
Classifier: Programming Language :: Python :: 3.7
Classifier: Programming Language :: Python :: 3.8
Classifier: Programming Language :: Python :: 3.9
